pandas_validate/Schema.py
pandas_validate/__init__.py
pandas_validate/columns/Column.py
pandas_validate/columns/DateTimeColumn.py
pandas_validate/columns/DecimalColumn.py
pandas_validate/columns/FloatColumn.py
pandas_validate/columns/IntColumn.py
pandas_validate/columns/TextColumn.py
pandas_validate/columns/__init__.py
pandas_validate-1.0.2.dist-info/LICENSE
pandas_validate-1.0.2.dist-info/METADATA
pandas_validate-1.0.2.dist-info/WHEEL
pandas_validate-1.0.2.dist-info/top_level.txt
pandas_validate-1.0.2.dist-info/RECORD
