Metadata-Version: 2.1
Name: pandas-validate
Version: 1.0.2
Summary: A python package used for validating pandas dataframes.
Author-email: Larry Green <larrygreen@duck.com>
License: MIT License
Project-URL: Homepage, https://github.com/larrygreen3/pandas-validate
Project-URL: Bug Tracker, https://github.com/larrygreen3/pandas-validate/issues
Keywords: pandas,validate,validation,schema,types
Classifier: Development Status :: 5 - Production/Stable
Classifier: Environment :: Console
Classifier: Intended Audience :: Science/Research
Classifier: Programming Language :: Python :: 3
Classifier: License :: OSI Approved :: MIT License
Classifier: Operating System :: OS Independent
Classifier: Topic :: Scientific/Engineering
Requires-Python: >=3.7
License-File: LICENSE
Requires-Dist: pandas
Requires-Dist: dateparser
Provides-Extra: build
Requires-Dist: build ; extra == 'build'
Requires-Dist: twine ; extra == 'build'
Provides-Extra: dev
Requires-Dist: pytest ; extra == 'dev'
